opstool/__about__.py
opstool/__init__.py
opstool/anlys/__init__.py
opstool/anlys/_help.py
opstool/anlys/_sec_analysis.py
opstool/anlys/_smart_analyze.py
opstool/opensees/__init__.py
opstool/opensees/friction_model.py
opstool/opensees/geom_transf.py
opstool/opensees/load_pattern.py
opstool/opensees/model.py
opstool/opensees/spy/__init__.py
opstool/opensees/spy/_manager/__init__.py
opstool/opensees/spy/_manager/_BaseHandler.py
opstool/opensees/spy/_manager/_ElementManager.py
opstool/opensees/spy/_manager/_LoadManager.py
opstool/opensees/spy/_manager/_MaterialManager.py
opstool/opensees/spy/_manager/_NodeManager.py
opstool/opensees/spy/_manager/_SectionManager.py
opstool/opensees/spy/_OpenSeesSpy.py
opstool/opensees/time_series.py
opstool/opensees/uniaxial_material.py
opstool/post/__init__.py
opstool/post/_combine_response_spectrum.py
opstool/post/_get_model_data_base.py
opstool/post/_get_response/__init__.py
opstool/post/_get_response/_get_contact_resp.py
opstool/post/_get_response/_get_fiber_sec_resp.py
opstool/post/_get_response/_get_frame_resp.py
opstool/post/_get_response/_get_link_resp.py
opstool/post/_get_response/_get_model_info_step.py
opstool/post/_get_response/_get_nodal_resp.py
opstool/post/_get_response/_get_plane_resp.py
opstool/post/_get_response/_get_sensitivity_resp.py
opstool/post/_get_response/_get_shell_resp.py
opstool/post/_get_response/_get_solid_resp.py
opstool/post/_get_response/_get_truss_resp.py
opstool/post/_get_response/_response_base.py
opstool/post/_post_utils.py
opstool/post/_unit_postprocess.py
opstool/post/eigen_data.py
opstool/post/linear_buckling_data.py
opstool/post/model_data.py
opstool/post/plot.py
opstool/post/responses_data.py
opstool/pre/__init__.py
opstool/pre/_model_data.py
opstool/pre/_model_mass.py
opstool/pre/_unit_system.py
opstool/pre/io/__init__.py
opstool/pre/io/_read_gmsh.py
opstool/pre/io/tcl2py.py
opstool/pre/load/__init__.py
opstool/pre/load/_gravity_load.py
opstool/pre/load/_load_distribution.py
opstool-1.0.26.dist-info/licenses/LICENCE.txt
opstool-1.0.26.dist-info/METADATA
opstool-1.0.26.dist-info/WHEEL
opstool-1.0.26.dist-info/RECORD
