Metadata-Version: 2.4
Name: opstool
Version: 1.0.26
Summary: opstool: A Python package for structural analysis and visualization using OpenSeesPy
License-File: LICENCE.txt
Author: Yexiang Yan
Author-email: yexiang_yan@outlook.com
Requires-Python: >=3.10,<3.13
Classifier: Programming Language :: Python :: 3
Classifier: Programming Language :: Python :: 3.10
Classifier: Programming Language :: Python :: 3.11
Classifier: Programming Language :: Python :: 3.12
Requires-Dist: gmsh (>=4.13.1)
Requires-Dist: imageio[ffmpeg] (>=2.36.1)
Requires-Dist: ipywidgets (>=8.1.5)
Requires-Dist: matplotlib (>=3.9.2)
Requires-Dist: netcdf4 (>=1.7.1.post2)
Requires-Dist: numpy (>=1.26.4)
Requires-Dist: pandas (>=2.2.3)
Requires-Dist: plotly (>=5.24.1)
Requires-Dist: pyvista (>=0.44.1)
Requires-Dist: rich (>=13.9.2)
Requires-Dist: scipy (>=1.14.1)
Requires-Dist: sectionproperties (>=3.4.0)
Requires-Dist: shapely (>=2.0.6)
Requires-Dist: tqdm (>=4.66.0)
Requires-Dist: trame (>=3.7.0)
Requires-Dist: trame-components (>=2.4.2)
Requires-Dist: trame-vtk (>=2.8.12)
Requires-Dist: trame-vuetify (>=2.7.2)
Requires-Dist: triangle (>=20230923)
Requires-Dist: typing-extensions (>=4.14.0,<5.0.0)
Requires-Dist: xarray (>=2024.10.0)
Requires-Dist: zarr (>=2.18)
Project-URL: Documentation, https://opstool.readthedocs.io/en/latest/index.html
Project-URL: Repository, https://github.com/yexiang1992/opstool
